faber_bench/__init__.py
faber_bench/application.py
faber_bench/artefact.py
faber_bench/artefact_ui.py
faber_bench/cli.py
faber_bench/dependencies.py
faber_bench/feature.py
faber_bench/feature_ui.py
faber_bench/init.py
faber_bench/init_ui.py
faber_bench/logging.py
faber_bench/main.py
faber_bench/main_ui.py
faber_bench/models.py
faber_bench/module.py
faber_bench/module_ui.py
faber_bench/resource_rc.py
faber_bench/settings.py
faber_bench/settings_ui.py
faber_bench/widgets.py
faber_bench-0.6.0.dev1.dist-info/LICENSE
faber_bench-0.6.0.dev1.dist-info/METADATA
faber_bench-0.6.0.dev1.dist-info/WHEEL
faber_bench-0.6.0.dev1.dist-info/entry_points.txt
faber_bench-0.6.0.dev1.dist-info/top_level.txt
faber_bench-0.6.0.dev1.dist-info/RECORD
