Metadata-Version: 2.1
Name: faber-bench
Version: 0.6.0.dev1
Summary: A graphical Faber interface.
Home-page: https://stefanseefeld.github.io/faber
Author: Stefan Seefeld
Author-email: stefan@seefeld.name
Maintainer: Stefan Seefeld
Maintainer-email: stefan@seefeld.name
License: BSL
Download-URL: https://github.com/stefanseefeld/faber/releases
Platform: UNKNOWN
Classifier: Environment :: Console
Classifier: Intended Audience :: Developers
Classifier: License :: OSI Approved :: Boost Software License 1.0 (BSL-1.0)
Classifier: Operating System :: OS Independent
Classifier: Topic :: Software Development :: Build Tools
Classifier: Topic :: Software Development :: Testing
Classifier: Programming Language :: Python
Requires-Python: >=3.6
Requires-Dist: faber
Requires-Dist: PyQt5
Requires-Dist: qasync
Requires-Dist: pydot
Requires-Dist: pygments
